rio_terrain/__init__.py
rio_terrain/cli/__init__.py
rio_terrain/cli/aspect.py
rio_terrain/cli/curvature.py
rio_terrain/cli/difference.py
rio_terrain/cli/extract.py
rio_terrain/cli/label.py
rio_terrain/cli/mad.py
rio_terrain/cli/quantiles.py
rio_terrain/cli/slice.py
rio_terrain/cli/slope.py
rio_terrain/cli/std.py
rio_terrain/cli/threshold.py
rio_terrain/cli/uncertainty.py
rio_terrain/core/__init__.py
rio_terrain/core/focalstatistics.py
rio_terrain/core/statistics.py
rio_terrain/core/terrain.py
rio_terrain/core/windowing.py
rio_terrain/tests/__init__.py
rio_terrain/tests/test_cli.py
rio_terrain/tools/__init__.py
rio_terrain/tools/messages.py
rio_terrain/tools/numbers.py
rio_terrain-0.0.29.dist-info/LICENSE.txt
rio_terrain-0.0.29.dist-info/METADATA
rio_terrain-0.0.29.dist-info/PKG-INFO.sync-conflict-20190117-125546-5T5JG6S
rio_terrain-0.0.29.dist-info/SOURCES.sync-conflict-20190117-125546-5T5JG6S.txt
rio_terrain-0.0.29.dist-info/WHEEL
rio_terrain-0.0.29.dist-info/entry_points.sync-conflict-20190117-125546-5T5JG6S.txt
rio_terrain-0.0.29.dist-info/entry_points.txt
rio_terrain-0.0.29.dist-info/top_level.txt
rio_terrain-0.0.29.dist-info/RECORD
