Metadata-Version: 2.1
Name: rio-terrain
Version: 0.0.29
Summary: Rasterio CLI plugin to perform common operations on single-band elevation rasters
Home-page: http://github.com/mrahnis/rio-terrain
Author: Michael Rahnis
Author-email: mike@topomatrix.com
License: BSD
Keywords: LiDAR,surveying,elevation,raster,DEM
Platform: UNKNOWN
Classifier: Development Status :: 3 - Alpha
Classifier: License :: OSI Approved :: BSD License
Classifier: Programming Language :: Python
Classifier: Programming Language :: Python :: 3
Classifier: Topic :: Scientific/Engineering :: GIS
Requires-Dist: numpy
Requires-Dist: scipy
Requires-Dist: matplotlib
Requires-Dist: rasterio
Requires-Dist: click
Requires-Dist: crick
